live_host/check_host.py
live_host-1.0.4.dist-info/LICENSE
live_host-1.0.4.dist-info/METADATA
live_host-1.0.4.dist-info/WHEEL
live_host-1.0.4.dist-info/top_level.txt
live_host-1.0.4.dist-info/RECORD
