Metadata-Version: 2.1
Name: live-host
Version: 1.0.4
Home-page: https://github.com/taqsblaze/Live-Host
Author: Tanaka Chinengundu
Author-email: tanakah30@gmail.com
License: Apache 2.0
Classifier: Development Status :: 3 - Alpha
Classifier: Intended Audience :: Developers
Classifier: Topic :: Software Development
Classifier: License :: OSI Approved :: MIT License
Requires-Python: >=3.8
License-File: LICENSE
Requires-Dist: pip
Requires-Dist: requests
